mongodb_data_layer/__init__.py
mongodb_data_layer/base.py
mongodb_data_layer/db.py
mongodb_data_layer/generate_model.py
mongodb_data_layer/templates/__init__.py
mongodb_data_layer/templates/model_template.py
mongodb_data_layer-1.2.dist-info/METADATA
mongodb_data_layer-1.2.dist-info/WHEEL
mongodb_data_layer-1.2.dist-info/entry_points.txt
mongodb_data_layer-1.2.dist-info/top_level.txt
mongodb_data_layer-1.2.dist-info/RECORD
