Metadata-Version: 2.2
Name: mongodb-data-layer
Version: 1.2
Summary: A data layer for mongodb
Author: Marjon Godito
Requires-Dist: pymongo
Requires-Dist: python-dotenv
Dynamic: author
Dynamic: description
Dynamic: description-content-type
Dynamic: requires-dist
Dynamic: summary
